{
  "GUID":"59d9b9",
  "Name":"Custom_Tile",
  "Transform":{
    "posX":-7.19022465,
    "posY":3.02071357,
    "posZ":-6.041224,
    "rotX":0.000121095749,
    "rotY":179.996185,
    "rotZ":0.0003022165,
    "scaleX":0.5657107,
    "scaleY":1.0,
    "scaleZ":0.5657107
  },
  "Nickname":"Body of a Yithian",
  "Description":"",
  "GMNotes":"",
  "AltLookAngle":{
    "x":0.0,
    "y":0.0,
    "z":0.0
  },
  "ColorDiffuse":{
    "r":1.0,
    "g":1.0,
    "b":1.0
  },
  "LayoutGroupSortIndex":0,
  "Value":0,
  "Locked":false,
  "Grid":false,
  "Snap":false,
  "IgnoreFoW":false,
  "MeasureMovement":false,
  "DragSelectable":true,
  "Autoraise":true,
  "Sticky":true,
  "Tooltip":true,
  "GridProjection":false,
  "HideWhenFaceDown":false,
  "Hands":false,
  "CustomImage":{
    "ImageURL":"http://cloud-3.steamusercontent.com/ugc/1763698230708495053/9F1C7D1CF0A5F67422EB475891FFBC8B4AAE7332/",
    "ImageSecondaryURL":"http://cloud-3.steamusercontent.com/ugc/1763698230708508538/25188B78E433A1487103B4D7FEBF8660AEBDB017/",
    "ImageScalar":1.0,
    "WidthScale":0.0,
    "CustomTile":{
      "Thickness":0.1,
      "Stackable":true,
      "Type":3,
      "Stretch":true
    }
  },
  "LuaScript":"",
  "LuaScriptState":"",
  "XmlUI":""
}