{
  "GUID":"f1af3a",
  "Name":"Custom_Tile",
  "Transform":{
    "posX":-0.8300723,
    "posY":1.06000137,
    "posZ":-2.92916632,
    "rotX":-1.88975428e-05,
    "rotY":179.999985,
    "rotZ":180.000031,
    "scaleX":0.5657107,
    "scaleY":1.0,
    "scaleZ":0.5657107
  },
  "Nickname":"Tony Morgan",
  "Description":"",
  "GMNotes":"",
  "AltLookAngle":{
    "x":0.0,
    "y":0.0,
    "z":0.0
  },
  "ColorDiffuse":{
    "r":1.0,
    "g":1.0,
    "b":1.0
  },
  "LayoutGroupSortIndex":0,
  "Value":0,
  "Locked":false,
  "Grid":false,
  "Snap":false,
  "IgnoreFoW":false,
  "MeasureMovement":false,
  "DragSelectable":true,
  "Autoraise":true,
  "Sticky":true,
  "Tooltip":true,
  "GridProjection":false,
  "HideWhenFaceDown":false,
  "Hands":false,
  "CustomImage":{
    "ImageURL":"http://cloud-3.steamusercontent.com/ugc/1763698230708200641/15C6BAF9B845A1180C9C02DFD64D8D4466B5B3B9/",
    "ImageSecondaryURL":"http://cloud-3.steamusercontent.com/ugc/1763698230708196357/33B209F29895F79441FD38C527C7B547347C095D/",
    "ImageScalar":1.0,
    "WidthScale":0.0,
    "CustomTile":{
      "Thickness":0.1,
      "Stackable":true,
      "Type":3,
      "Stretch":true
    }
  },
  "LuaScript":"",
  "LuaScriptState":"",
  "XmlUI":""
}