{
  "Tags":["PlayerCard","Asset"],
  "GUID":"1bf025",
  "Name":"Card",
  "Transform":{
    "posX":78.58734,
    "posY":3.33044648,
    "posZ":7.553613,
    "rotX":359.918671,
    "rotY":269.999664,
    "rotZ":0.603583932,
    "scaleX":1.0,
    "scaleY":1.0,
    "scaleZ":1.0
  },
  "Nickname":"Anyu",
  "Description":"Faithful Companion",
  "GMNotes":"{\n  \"id\": \"08738\",\n  \"type\": \"Asset\",\n  \"class\": \"Neutral\",\n  \"cost\": 3,\n  \"traits\": \"Ally. Creature.\",\n  \"permanent\": false,\n  \"weakness\": false,\n  \"agilityIcons\": 1,\n  \"wildIcons\": 1,\n  \"cycle\": \"Edge of the Earth\"\n}",
  "AltLookAngle":{
    "x":0.0,
    "y":0.0,
    "z":0.0
  },
  "ColorDiffuse":{
    "r":0.713235259,
    "g":0.713235259,
    "b":0.713235259
  },
  "LayoutGroupSortIndex":0,
  "Value":0,
  "Locked":false,
  "Grid":true,
  "Snap":true,
  "IgnoreFoW":false,
  "MeasureMovement":false,
  "DragSelectable":true,
  "Autoraise":true,
  "Sticky":true,
  "Tooltip":true,
  "GridProjection":false,
  "HideWhenFaceDown":true,
  "Hands":true,
  "CardID":452308,
  "CustomDeck":{
    "4523":{
      "FaceURL":"http://cloud-3.steamusercontent.com/ugc/1858293462583875023/F146A60AEF1FBC9B5FC96189BC1894C468C1E811/",
      "BackURL":"https://i.imgur.com/EcbhVuh.jpg/",
      "NumWidth":5,
      "NumHeight":2,
      "BackIsHidden":true,
      "UniqueBack":false,
      "Type":0
    }
  },
  "LuaScript":"",
  "LuaScriptState":"",
  "XmlUI":"",
  "SidewaysCard":false
}