{
  "GUID":"0d621f",
  "Name":"Custom_Tile",
  "Transform":{
    "posX":-8.374089,
    "posY":3.03399682,
    "posZ":-0.189263374,
    "rotX":358.7159,
    "rotY":179.985214,
    "rotZ":1.32161307,
    "scaleX":0.5657107,
    "scaleY":1.0,
    "scaleZ":0.5657107
  },
  "Nickname":"Leo Anderson",
  "Description":"",
  "GMNotes":"",
  "AltLookAngle":{
    "x":0.0,
    "y":0.0,
    "z":0.0
  },
  "ColorDiffuse":{
    "r":1.0,
    "g":1.0,
    "b":1.0
  },
  "LayoutGroupSortIndex":0,
  "Value":0,
  "Locked":false,
  "Grid":false,
  "Snap":false,
  "IgnoreFoW":false,
  "MeasureMovement":false,
  "DragSelectable":true,
  "Autoraise":true,
  "Sticky":true,
  "Tooltip":true,
  "GridProjection":false,
  "HideWhenFaceDown":false,
  "Hands":false,
  "CustomImage":{
    "ImageURL":"http://cloud-3.steamusercontent.com/ugc/1763698230707749544/BD7A64A90A1FFA471FA4856CB29CCC273B18C7AE/",
    "ImageSecondaryURL":"http://cloud-3.steamusercontent.com/ugc/1763698230707756335/CC5AFDEA8E26679935805BC32838833E8B12F215/",
    "ImageScalar":1.0,
    "WidthScale":0.0,
    "CustomTile":{
      "Thickness":0.1,
      "Stackable":true,
      "Type":3,
      "Stretch":true
    }
  },
  "LuaScript":"",
  "LuaScriptState":"",
  "XmlUI":""
}