{
  "GUID":"3b3c0a",
  "Name":"Card",
  "Transform":{
    "posX":-68.997345,
    "posY":1.49685133,
    "posZ":-92.3112946,
    "rotX":0.0208098143,
    "rotY":269.999939,
    "rotZ":0.0167921279,
    "scaleX":1.0,
    "scaleY":1.0,
    "scaleZ":1.0
  },
  "Nickname":"Drawing the Sign",
  "Description":"Basic Weakness",
  "GMNotes":"",
  "AltLookAngle":{
    "x":0.0,
    "y":0.0,
    "z":0.0
  },
  "ColorDiffuse":{
    "r":0.713235259,
    "g":0.713235259,
    "b":0.713235259
  },
  "LayoutGroupSortIndex":0,
  "Value":0,
  "Locked":false,
  "Grid":true,
  "Snap":true,
  "IgnoreFoW":false,
  "MeasureMovement":false,
  "DragSelectable":true,
  "Autoraise":true,
  "Sticky":true,
  "Tooltip":true,
  "GridProjection":false,
  "HideWhenFaceDown":true,
  "Hands":true,
  "CardID":431111,
  "CustomDeck":{
    "4311":{
      "FaceURL":"http://cloud-3.steamusercontent.com/ugc/775107869048626382/DA1F5817A4067A74D883201F1AFAC096646A455B/",
      "BackURL":"https://i.imgur.com/EcbhVuh.jpg/",
      "NumWidth":10,
      "NumHeight":7,
      "BackIsHidden":true,
      "UniqueBack":false,
      "Type":0
    }
  },
  "LuaScript":"",
  "LuaScriptState":"",
  "XmlUI":"",
  "SidewaysCard":false
}