{
  "Tags":["tdlmat_memory_object"],
  "GUID":"995d75",
  "Name":"Custom_Token",
  "Transform":{
    "posX":40.2900467,
    "posY":1.38221669,
    "posZ":-79.61988,
    "rotX":358.457123,
    "rotY":269.980774,
    "rotZ":0.0167763848,
    "scaleX":1.0,
    "scaleY":1.0,
    "scaleZ":1.0
  },
  "Nickname":"TDL - 8A",
  "Description":"",
  "GMNotes":"",
  "AltLookAngle":{
    "x":0.0,
    "y":0.0,
    "z":0.0
  },
  "ColorDiffuse":{
    "r":1.0,
    "g":1.0,
    "b":1.0
  },
  "LayoutGroupSortIndex":0,
  "Value":0,
  "Locked":false,
  "Grid":true,
  "Snap":true,
  "IgnoreFoW":false,
  "MeasureMovement":false,
  "DragSelectable":true,
  "Autoraise":true,
  "Sticky":true,
  "Tooltip":true,
  "GridProjection":false,
  "HideWhenFaceDown":false,
  "Hands":false,
  "CustomImage":{
    "ImageURL":"https://i.ibb.co/0XcnxFD/Dunwich-8-Lost-in-Time-amp-Space-Lino-Drieghe.jpg",
    "ImageSecondaryURL":"",
    "ImageScalar":1.0,
    "WidthScale":0.0,
    "CustomToken":{
      "Thickness":0.1,
      "MergeDistancePixels":15.0,
      "StandUp":false,
      "Stackable":false
    }
  },
  "LuaScript":"",
  "LuaScriptState":"",
  "XmlUI":""
}