{
  "GUID":"9ce4ab",
  "Name":"Custom_Tile",
  "Transform":{
    "posX":-8.853577,
    "posY":3.74371839,
    "posZ":6.87800741,
    "rotX":347.662476,
    "rotY":311.9395,
    "rotZ":98.66789,
    "scaleX":0.81,
    "scaleY":1.0,
    "scaleZ":0.81
  },
  "Nickname":"0",
  "Description":"",
  "GMNotes":"",
  "AltLookAngle":{
    "x":0.0,
    "y":0.0,
    "z":0.0
  },
  "ColorDiffuse":{
    "r":1.0,
    "g":1.0,
    "b":1.0
  },
  "LayoutGroupSortIndex":0,
  "Value":0,
  "Locked":false,
  "Grid":true,
  "Snap":true,
  "IgnoreFoW":false,
  "MeasureMovement":false,
  "DragSelectable":true,
  "Autoraise":true,
  "Sticky":true,
  "Tooltip":true,
  "GridProjection":false,
  "HideWhenFaceDown":false,
  "Hands":false,
  "CustomImage":{
    "ImageURL":"https://i.imgur.com/btEtVfd.png",
    "ImageSecondaryURL":"",
    "ImageScalar":1.0,
    "WidthScale":0.0,
    "CustomTile":{
      "Thickness":0.1,
      "Stackable":false,
      "Type":2,
      "Stretch":true
    }
  },
  "LuaScript":"",
  "LuaScriptState":"",
  "XmlUI":""
}